omega_gpio
