Metadata-Version: 1.0
Name: omega-gpio
Version: 1.1
Summary: Simple GPIO for the Onion Omega device
Home-page: https://github.com/angstwad/omega-gpio
Author: Paul Durivage
Author-email: pauldurivage@gmail.com
License: Apache 2.0
Platform: UNKNOWN
